sqlmap_client/__init__.py
sqlmap_client/api_client.py
sqlmap_client/configuration.py
sqlmap_client/exceptions.py
sqlmap_client/rest.py
sqlmap_client/api/__init__.py
sqlmap_client/api/default_api.py
sqlmap_client/models/__init__.py
sqlmap_client/models/create_task_response.py
sqlmap_client/models/get_task_options_response.py
sqlmap_client/models/standard_response.py
sqlmap_client/models/task_log.py
sqlmap_client/models/task_options.py
sqlmap_client/models/task_status.py
sqlmap_client/models/task_url.py
sqlmap_client-0.0.1.dist-info/LICENSE
sqlmap_client-0.0.1.dist-info/METADATA
sqlmap_client-0.0.1.dist-info/WHEEL
sqlmap_client-0.0.1.dist-info/top_level.txt
sqlmap_client-0.0.1.dist-info/RECORD
