Metadata-Version: 2.1
Name: sqlmap-client
Version: 0.0.1
Summary: SQLMap Server API
Home-page: https://github.com/ddoroshevsky/sqlmap_python_client
Author: OpenAPI Generator community
Author-email: team@openapitools.org
License: UNKNOWN
Keywords: OpenAPI,OpenAPI-Generator,SQLMap Server API
Platform: UNKNOWN
Requires-Dist: urllib3 (>=1.15)
Requires-Dist: six (>=1.10)
Requires-Dist: certifi
Requires-Dist: python-dateutil
